surface_construct/__init__.py
surface_construct/db.py
surface_construct/default_parameter.py
surface_construct/sg_sampler.py
surface_construct/structures/__init__.py
surface_construct/structures/adsorbate.py
surface_construct/structures/combiner.py
surface_construct/structures/pymsym_test.py
surface_construct/structures/surface.py
surface_construct/structures/surface_grid.py
surface_construct/tasks/__init__.py
surface_construct/tasks/afm.py
surface_construct/tasks/sitesampling.py
surface_construct/tasks/taskbase.py
surface_construct/tasks/terminations.py
surface_construct/utils/__init__.py
surface_construct/utils/atoms.py
surface_construct/utils/geometry.py
surface_construct/utils/pymsym_wrapper.py
surface_construct/utils/spglib_wrapper.py
surface_construct/utils/weight_functions.py
surface_construct-0.12.dist-info/licenses/LICENSE
surface_construct-0.12.dist-info/METADATA
surface_construct-0.12.dist-info/WHEEL
surface_construct-0.12.dist-info/top_level.txt
surface_construct-0.12.dist-info/RECORD
