Metadata-Version: 2.4
Name: surface_construct
Version: 0.12
Summary: Surface construction and surface reaction sampling tools.
Home-page: https://gitee.com/pjren/surface_construct/
Author: ren
Author-email: 0403114076@163.com
License: GPL
Classifier: Programming Language :: Python :: 3
Classifier: Operating System :: OS Independent
License-File: LICENSE
Requires-Dist: ase
Requires-Dist: networkx
Requires-Dist: spglib
Requires-Dist: pandas
Requires-Dist: tqdm
Requires-Dist: scikit-learn
Requires-Dist: scikit-image
Dynamic: author
Dynamic: author-email
Dynamic: classifier
Dynamic: description
Dynamic: description-content-type
Dynamic: home-page
Dynamic: license
Dynamic: license-file
Dynamic: requires-dist
Dynamic: summary
